mcxpy/__init__.py
mcxpy/__init__.pyi
mcxpy/mcx.py
mcxpy/mcx.pyi
mcxpy/py.typed
mcxpy-0.0.3.dist-info/LICENSE
mcxpy-0.0.3.dist-info/METADATA
mcxpy-0.0.3.dist-info/WHEEL
mcxpy-0.0.3.dist-info/top_level.txt
mcxpy-0.0.3.dist-info/RECORD
