Metadata-Version: 2.1
Name: mcxpy
Version: 0.0.3
Summary: For fetching mcx data
Author: Tapan Hazarika
License: MIT License
Project-URL: Homepage, https://github.com/Tapanhaz/mcxpy
Classifier: Programming Language :: Python :: 3
Classifier: License :: OSI Approved :: MIT License
Classifier: Operating System :: OS Independent
License-File: LICENSE
Requires-Dist: pandas (>=2.0.0)
Requires-Dist: requests
